deepsecrets/.pytest_cache/.gitignore
deepsecrets/.pytest_cache/CACHEDIR.TAG
deepsecrets/.pytest_cache/README.md
deepsecrets/.pytest_cache/v/cache/lastfailed
deepsecrets/.pytest_cache/v/cache/nodeids
deepsecrets/.pytest_cache/v/cache/stepwise
deepsecrets/__init__.py
deepsecrets/__main__.py
deepsecrets/cli.py
deepsecrets/config.py
deepsecrets/core/engines/__init__.py
deepsecrets/core/engines/hashed_secret.py
deepsecrets/core/engines/iengine.py
deepsecrets/core/engines/regex.py
deepsecrets/core/engines/semantic.py
deepsecrets/core/helpers/content_analyzer.py
deepsecrets/core/helpers/entropy.py
deepsecrets/core/model/__init__.py
deepsecrets/core/model/file.py
deepsecrets/core/model/finding.py
deepsecrets/core/model/rules/__init__.py
deepsecrets/core/model/rules/exlcuded_path.py
deepsecrets/core/model/rules/false_finding.py
deepsecrets/core/model/rules/hashed_secret.py
deepsecrets/core/model/rules/hashing.py
deepsecrets/core/model/rules/regex.py
deepsecrets/core/model/rules/rule.py
deepsecrets/core/model/rules/semantic.py
deepsecrets/core/model/semantic.py
deepsecrets/core/model/token.py
deepsecrets/core/modes/iscan_mode.py
deepsecrets/core/rulesets/excluded_paths.py
deepsecrets/core/rulesets/false_findings.py
deepsecrets/core/rulesets/hashed_secrets.py
deepsecrets/core/rulesets/ibuilder.py
deepsecrets/core/rulesets/regex.py
deepsecrets/core/tokenizers/__init__.py
deepsecrets/core/tokenizers/full_content.py
deepsecrets/core/tokenizers/helpers/__init__.py
deepsecrets/core/tokenizers/helpers/semantic/__init__.py
deepsecrets/core/tokenizers/helpers/semantic/language.py
deepsecrets/core/tokenizers/helpers/semantic/var_detection/__init__.py
deepsecrets/core/tokenizers/helpers/semantic/var_detection/detector.py
deepsecrets/core/tokenizers/helpers/semantic/var_detection/rules.py
deepsecrets/core/tokenizers/helpers/spot_improvements.py
deepsecrets/core/tokenizers/helpers/type_stream.py
deepsecrets/core/tokenizers/itokenizer.py
deepsecrets/core/tokenizers/lexer.py
deepsecrets-1.4.0.dist-info/LICENSE
deepsecrets-1.4.0.dist-info/METADATA
deepsecrets-1.4.0.dist-info/WHEEL
deepsecrets-1.4.0.dist-info/entry_points.txt
deepsecrets-1.4.0.dist-info/RECORD
