Metadata-Version: 2.3
Name: deepsecrets
Version: 1.4.0
Summary: A better tool for secrets search
License: MIT
Keywords: security,secrets,credentials,scanning,appsec,code,search
Author: Nikolai Khechumov
Author-email: khechumov@gmail.com
Maintainer: Nikolai Khechumov
Maintainer-email: khechumov@gmail.com
Requires-Python: >=3.9,<4.0.0
Classifier: Programming Language :: Python :: 3
Classifier: License :: OSI Approved :: MIT License
Classifier: Operating System :: OS Independent
Classifier: Environment :: Console
Classifier: Topic :: Security
Requires-Dist: aenum (==3.1.15)
Requires-Dist: dotwiz (==0.4.0)
Requires-Dist: jschema-to-python (==1.2.3)
Requires-Dist: jsx-lexer (==2.0.1)
Requires-Dist: mmh3 (==5.1.0)
Requires-Dist: ordered-set (==4.1.0)
Requires-Dist: puppetparser (==0.2.14)
Requires-Dist: pydantic (==2.10.6)
Requires-Dist: pygments (==2.19.1)
Requires-Dist: pyyaml (==6.0.2)
Requires-Dist: regex (==2024.11.6)
Requires-Dist: sarif-om (==1.0.4)
Requires-Dist: textual (==1.0.0)
Project-URL: Bug Tracker, https://github.com/ntoskernel/deepsecrets/issues
Project-URL: Homepage, https://owasp.org/www-project-deepsecrets/
Project-URL: Repository, https://github.com/ntoskernel/deepsecrets
